hkibg_qcloud_cos_keeper/__init__.py
hkibg_qcloud_cos_keeper/args_util.py
hkibg_qcloud_cos_keeper/config_util.py
hkibg_qcloud_cos_keeper/cos_util.py
hkibg_qcloud_cos_keeper/date_util.py
hkibg_qcloud_cos_keeper/decorator.py
hkibg_qcloud_cos_keeper/generic_util.py
hkibg_qcloud_cos_keeper-0.0.3.data/scripts/qcloud_cos_keeper_file_cleaner.py
hkibg_qcloud_cos_keeper-0.0.3.data/scripts/qcloud_cos_keeper_file_rotator.py
hkibg_qcloud_cos_keeper-0.0.3.data/scripts/qcloud_cos_keeper_file_uploader.py
hkibg_qcloud_cos_keeper-0.0.3.dist-info/METADATA
hkibg_qcloud_cos_keeper-0.0.3.dist-info/RECORD
hkibg_qcloud_cos_keeper-0.0.3.dist-info/WHEEL
hkibg_qcloud_cos_keeper-0.0.3.dist-info/top_level.txt
