Metadata-Version: 2.1
Name: hkibg-qcloud-cos-keeper
Version: 0.0.3
Summary: a qcloud cos file/log keeper for hkibg
Home-page: https://bitbucket.org/pongpersonal/hkibg_qcloud_cos_keeper/src/master/
Author: Luk Chun Pong
Author-email: pongluk@tencent.com
License: UNKNOWN
Platform: UNKNOWN
Classifier: Programming Language :: Python :: 3
Classifier: License :: OSI Approved :: MIT License
Classifier: Operating System :: OS Independent
Requires-Dist: cos-python-sdk-v5 (==1.5.5)
Requires-Dist: pytz
Requires-Dist: tzlocal
